Metadata-Version: 2.1
Name: newcaclculator
Version: 1.0.0
Summary: A description of pytoolboxtwo
Home-page: https://github.com/SoujanyaRAcharya/newcalculator
Author: soujanya
Author-email: soujanyaacharya2001@gmail.com
Classifier: Development Status :: 5 - Production/Stable
Classifier: Intended Audience :: Developers
Classifier: License :: OSI Approved :: MIT License
Classifier: Operating System :: OS Independent
Classifier: Programming Language :: Python :: 3
Classifier: Programming Language :: Python :: 3.6
Classifier: Programming Language :: Python :: 3.7
Classifier: Programming Language :: Python :: 3.8
Classifier: Programming Language :: Python :: 3.9
License-File: Licence
